pyaxp-0.2.4.dist-info/METADATA
pyaxp-0.2.4.dist-info/WHEEL
pyaxp.libs/libgcc_s-e52197c3.so.1
pyaxp/__init__.py
pyaxp/pyaxp.cpython-311-aarch64-linux-musl.so
pyaxp-0.2.4.dist-info/RECORD
