Metadata-Version: 2.4
Name: pyaxp
Version: 0.2.4
Classifier: Programming Language :: Rust
Classifier: Programming Language :: Python :: Implementation :: CPython
Classifier: Programming Language :: Python :: Implementation :: PyPy
Summary: <yaxp-cli ⚡> Yet Another XSD Parser
Author-email: Jeroen <jeroen@flexworks.eu>
Requires-Python: >=3.10
Project-URL: Homepage, https://github.com/opensourceworks-org/yaxp
Project-URL: Documentation, https://github.com/opensourceworks-org/yaxp/blob/main/crates/pyaxp/README.md
Project-URL: Repository, https://github.com/opensourceworks-org/yaxp/blob/main/crates/pyaxp
Project-URL: BugTracker, https://github.com/opensourceworks-org/yaxp/issues
